{"command": "/home/cb76/cb761223/small_samples/build/qap /home/cb76/cb761223/small_samples/qap/problems/chr10a.dat", "number_of_runs": 5, "runs": [{"real": 0.02, "user": 0.00, "sys": 0.00, "max_mem": 1484},{"real": 0.00, "user": 0.00, "sys": 0.00, "max_mem": 1480},{"real": 0.00, "user": 0.00, "sys": 0.00, "max_mem": 1500},{"real": 0.00, "user": 0.00, "sys": 0.00, "max_mem": 1496},{"real": 0.00, "user": 0.00, "sys": 0.00, "max_mem": 1428}], "mean": {"real": 0.004, "user": 0.000, "sys": 0.000, "max_mem": 1477.600}, "variance": {"real": 0.000, "user": 0.000, "sys": 0.000, "max_mem": 669.440}}
